latex_symbol_manager.cpython-310-x86_64-linux-gnu.so
latex_symbol_manager.pyi
LatexSymbolManager_z7-7.3.2201261049.dist-info/WHEEL
LatexSymbolManager_z7-7.3.2201261049.dist-info/top_level.txt
LatexSymbolManager_z7-7.3.2201261049.dist-info/RECORD
LatexSymbolManager_z7-7.3.2201261049.dist-info/METADATA
LatexSymbolManager_z7-7.3.2201261049.dist-info/zip-safe
LatexSymbolManager_z7-7.3.2201261049.dist-info/entry_points.txt
