Metadata-Version: 2.1
Name: LatexSymbolManager-z7
Version: 7.3.2201261049
Summary: UNKNOWN
Home-page: https://github.com/zupermind/PACKAGENAME
Author: Andrea Censi
Author-email: info@zupermind.com
License: UNKNOWN
Platform: UNKNOWN
Requires-Dist: PyYAML
Requires-Dist: latex-gen-z7
Requires-Dist: zuper-commons-z7
Requires-Dist: zuper-ipce-z7
Requires-Dist: zuper-typing-z7
Provides-Extra: test
